Metadata-Version: 2.4
Name: mseep-bitrise-mcp
Version: 0.1.4
Summary: Add your description here
Author-email: mseep <support@skydeck.ai>
License: MIT
Requires-Python: >=3.12.6
License-File: LICENSE
Requires-Dist: httpx>=0.28.1
Requires-Dist: mcp[cli]>=1.6.0
Dynamic: license-file
